{
  "name": "Lend Default List",
  "timestamp": "2022-06-16T11:45:09Z",
  "version": {
    "major": 4,
    "minor": 0,
    "patch": 0
  },
  "tokens": [
    {
      "in": {
        "name": "USDC",
        "symbol": "USDC",
        "address": "0xAC8B36d26f704c43cA3AAC6682083786eB83cf38",
        "chainId": 97,
        "decimals": 18,
        "logoURI": "https://www.centre.io/hubfs/usdc-icon-86074d9d49.png"
      },
      "out": {
        "name": "ibUSDC",
        "symbol": "ibUSDC",
        "address": "0xdfc169de2454CB5b925034433742956c416EE6C1",
        "chainId": 97,
        "decimals": 18,
        "logoURI": "https://www.centre.io/hubfs/usdc-icon-86074d9d49.png"
      }
    }
  ]
}
